tencent/cloud/common/__init__.py
tencent/cloud/common/idna_ssl.py
tencent/cloud/common/typing_extensions.py
tencent/cloud/common/aiohttp/__init__.py
tencent/cloud/common/aiohttp/abc.py
tencent/cloud/common/aiohttp/base_protocol.py
tencent/cloud/common/aiohttp/client.py
tencent/cloud/common/aiohttp/client_exceptions.py
tencent/cloud/common/aiohttp/client_proto.py
tencent/cloud/common/aiohttp/client_reqrep.py
tencent/cloud/common/aiohttp/client_ws.py
tencent/cloud/common/aiohttp/connector.py
tencent/cloud/common/aiohttp/cookiejar.py
tencent/cloud/common/aiohttp/formdata.py
tencent/cloud/common/aiohttp/hdrs.py
tencent/cloud/common/aiohttp/helpers.py
tencent/cloud/common/aiohttp/http.py
tencent/cloud/common/aiohttp/http_exceptions.py
tencent/cloud/common/aiohttp/http_parser.py
tencent/cloud/common/aiohttp/http_websocket.py
tencent/cloud/common/aiohttp/http_writer.py
tencent/cloud/common/aiohttp/locks.py
tencent/cloud/common/aiohttp/log.py
tencent/cloud/common/aiohttp/multipart.py
tencent/cloud/common/aiohttp/payload.py
tencent/cloud/common/aiohttp/payload_streamer.py
tencent/cloud/common/aiohttp/pytest_plugin.py
tencent/cloud/common/aiohttp/resolver.py
tencent/cloud/common/aiohttp/streams.py
tencent/cloud/common/aiohttp/tcp_helpers.py
tencent/cloud/common/aiohttp/test_utils.py
tencent/cloud/common/aiohttp/tracing.py
tencent/cloud/common/aiohttp/typedefs.py
tencent/cloud/common/aiohttp/web.py
tencent/cloud/common/aiohttp/web_app.py
tencent/cloud/common/aiohttp/web_exceptions.py
tencent/cloud/common/aiohttp/web_fileresponse.py
tencent/cloud/common/aiohttp/web_log.py
tencent/cloud/common/aiohttp/web_middlewares.py
tencent/cloud/common/aiohttp/web_protocol.py
tencent/cloud/common/aiohttp/web_request.py
tencent/cloud/common/aiohttp/web_response.py
tencent/cloud/common/aiohttp/web_routedef.py
tencent/cloud/common/aiohttp/web_runner.py
tencent/cloud/common/aiohttp/web_server.py
tencent/cloud/common/aiohttp/web_urldispatcher.py
tencent/cloud/common/aiohttp/web_ws.py
tencent_cloud_sdk_common-0.1.5.dist-info/LICENSE
tencent_cloud_sdk_common-0.1.5.dist-info/METADATA
tencent_cloud_sdk_common-0.1.5.dist-info/WHEEL
tencent_cloud_sdk_common-0.1.5.dist-info/top_level.txt
tencent_cloud_sdk_common-0.1.5.dist-info/RECORD
